eventory.py
eventory_droox-0.1.0.dist-info/LICENSE
eventory_droox-0.1.0.dist-info/METADATA
eventory_droox-0.1.0.dist-info/WHEEL
eventory_droox-0.1.0.dist-info/top_level.txt
eventory_droox-0.1.0.dist-info/RECORD
